loggingtools/__init__.py
loggingtools/_version.py
loggingtools/cli.py
loggingtools/config.py
loggingtools/log_with.py
loggingtools/setup_logging.py
loggingtools/templates/logging.ini
loggingtools/templates/logging.json
loggingtools/templates/logging.yml
loggingtools/tests/__init__.py
loggingtools/tests/test_cli.py
loggingtools/tests/test_loggingtools.py
loggingtools-0.0.4.dist-info/DESCRIPTION.rst
loggingtools-0.0.4.dist-info/METADATA
loggingtools-0.0.4.dist-info/RECORD
loggingtools-0.0.4.dist-info/WHEEL
loggingtools-0.0.4.dist-info/entry_points.txt
loggingtools-0.0.4.dist-info/metadata.json
loggingtools-0.0.4.dist-info/top_level.txt
