Metadata-Version: 2.0
Name: loggingtools
Version: 0.0.4
Summary: Python logging dictionary configuration from yaml, json or dictionary.
Home-page: https://github.com/jaantollander/loggingtools.git
Author: Jaan Tollander de Balsch
Author-email: jaan.tollander@gmail.com
License: MIT
Platform: UNKNOWN
Classifier: Development Status :: 3 - Alpha
Classifier: Intended Audience :: Developers
Classifier: License :: OSI Approved :: MIT License
Classifier: Natural Language :: English
Classifier: Programming Language :: Python :: 3 :: Only
Classifier: Programming Language :: Python :: 3.3
Classifier: Programming Language :: Python :: 3.4
Classifier: Programming Language :: Python :: 3.5
Classifier: Programming Language :: Python :: 3.6
Requires-Dist: click
Requires-Dist: colorama
Requires-Dist: colorlog
Requires-Dist: ruamel.yaml
